README.md
setup.cfg
setup.py
RetrievalModels/__init__.py
RetrievalModels/best_match_25.py
RetrievalModels/jelinek_mercer_language_model.py
RetrievalModels/vector_space_model.py
RetrievalModels.egg-info/PKG-INFO
RetrievalModels.egg-info/SOURCES.txt
RetrievalModels.egg-info/dependency_links.txt
RetrievalModels.egg-info/not-zip-safe
RetrievalModels.egg-info/requires.txt
RetrievalModels.egg-info/top_level.txt
RetrievalModels/trec_eval/__init__.py
RetrievalModels/trec_eval/importer.py
RetrievalModels/trec_eval/trec_eval.py
RetrievalModels/utils/__init__.py
RetrievalModels/utils/cache.py
RetrievalModels/utils/collections.py
RetrievalModels/utils/inverted_index.py