Metadata-Version: 1.0
Name: RetrievalModels
Version: 0.0.1
Summary: Information Retrival
Home-page: UNKNOWN
Author: hrwX
Author-email: UNKNOWN
License: MIT
Platform: UNKNOWN
